{
	"aspect-ratio": {
		"1x1": {
			"name": "1x1",
			"value": "1",
			"description": "This is to make an item square",
			"type": "ratio",
			"category": "aspect-ratio",
			"themeable": false,
			"meta": {
				"public": true,
				"depracted": false,
				"SassVariable": true,
				"CSSCustomProperty": false
			}
		},
		"4x3": {
			"name": "4x3",
			"value": "1.3333333333333333",
			"description": "This is to make an item 4:3",
			"type": "ratio",
			"category": "aspect-ratio",
			"themeable": false,
			"meta": {
				"public": true,
				"depracted": false,
				"SassVariable": true,
				"CSSCustomProperty": false
			}
		},
		"16x9": {
			"name": "16x9",
			"value": "1.7777777777777777",
			"description": "This is to make an item 16:9",
			"type": "ratio",
			"category": "aspect-ratio",
			"themeable": false,
			"meta": {
				"public": true,
				"depracted": false,
				"SassVariable": true,
				"CSSCustomProperty": false
			}
		}
	}
}